PandasLibrary/__init__.py
robotframework_pandaslibrary-0.0.1.dist-info/LICENSE
robotframework_pandaslibrary-0.0.1.dist-info/METADATA
robotframework_pandaslibrary-0.0.1.dist-info/WHEEL
robotframework_pandaslibrary-0.0.1.dist-info/top_level.txt
robotframework_pandaslibrary-0.0.1.dist-info/RECORD
